dria/.DS_Store
dria/__init__.py
dria/config/__init__.py
dria/config/config.py
dria/constants.py
dria/core/__init__.py
dria/core/api/__init__.py
dria/core/api/api.py
dria/core/api/api_local.py
dria/core/client/__init__.py
dria/core/client/client.py
dria/core/client/client_local.py
dria/core/index.py
dria/core/index_local.py
dria/core/proto/serialization.py
dria/core/proto/vector_pb2.py
dria/exceptions/__init__.py
dria/exceptions/exceptions.py
dria/models/__init__.py
dria/models/models.py
dria/models/models_local.py
dria-0.1.20.dist-info/LICENSE
dria-0.1.20.dist-info/METADATA
dria-0.1.20.dist-info/WHEEL
dria-0.1.20.dist-info/RECORD
