Metadata-Version: 2.1
Name: dria
Version: 0.1.20
Summary: A Python client for the Dria API.
Author: Anil Berk Altuner
Author-email: anil@firstbatch.xyz
Requires-Python: >=3.8,<4.0
Classifier: Programming Language :: Python :: 3
Classifier: Programming Language :: Python :: 3.8
Classifier: Programming Language :: Python :: 3.9
Classifier: Programming Language :: Python :: 3.10
Classifier: Programming Language :: Python :: 3.11
Classifier: Programming Language :: Python :: 3.12
Requires-Dist: dataclasses-json (>=0.6.4,<0.7.0)
Requires-Dist: protobuf (==4.25.2)
Requires-Dist: pydantic (>=2.6.0,<3.0.0)
Requires-Dist: requests (>=2.25.1,<3.0.0)
